[
  {
    "low": 4496.9,
    "high": 4496.9,
    "close": 4496.9,
    "time": 1650532808928
  },
  {
    "low": 4496.9,
    "high": 4496.9,
    "close": 4496.9,
    "time": 1650532811840
  },
  {
    "low": 4496.9,
    "high": 4497,
    "close": 4496.9,
    "time": 1650532815681
  },
  {
    "low": 4496.9,
    "high": 4496.9,
    "close": 4496.9,
    "time": 1650532817834
  },
  {
    "low": 4496.9,
    "high": 4497,
    "close": 4497,
    "time": 1650532818893
  },
  {
    "low": 4496.9,
    "high": 4496.9,
    "close": 4496.9,
    "time": 1650532823071
  },
  {
    "low": 4496.9,
    "high": 4497,
    "close": 4496.9,
    "time": 1650532824388
  },
  {
    "low": 4496.6,
    "high": 4496.9,
    "close": 4496.6,
    "time": 1650532825414
  },
  {
    "low": 4496.7,
    "high": 4496.8,
    "close": 4496.8,
    "time": 1650532826450
  },
  {
    "low": 4496.6,
    "high": 4496.7,
    "close": 4496.6,
    "time": 1650532828203
  },
  {
    "low": 4496.7,
    "high": 4496.9,
    "close": 4496.9,
    "time": 1650532829994
  },
  {
    "low": 4496.6,
    "high": 4496.9,
    "close": 4496.9,
    "time": 1650532831541
  },
  {
    "low": 4496.7,
    "high": 4497,
    "close": 4497,
    "time": 1650532832744
  },
  {
    "low": 4496.9,
    "high": 4497.1,
    "close": 4496.9,
    "time": 1650532835275
  },
  {
    "low": 4497.1,
    "high": 4497.1,
    "close": 4497.1,
    "time": 1650532836501
  },
  {
    "low": 4496.8,
    "high": 4497.1,
    "close": 4496.9,
    "time": 1650532837949
  },
  {
    "low": 4496.9,
    "high": 4497,
    "close": 4497,
    "time": 1650532839270
  },
  {
    "low": 4496.9,
    "high": 4496.9,
    "close": 4496.9,
    "time": 1650532841925
  },
  {
    "low": 4496.8,
    "high": 4496.8,
    "close": 4496.8,
    "time": 1650532844906
  },
  {
    "low": 4496.8,
    "high": 4497.1,
    "close": 4496.8,
    "time": 1650532847710
  },
  {
    "low": 4496.8,
    "high": 4497.1,
    "close": 4496.8,
    "time": 1650532849126
  },
  {
    "low": 4496.7,
    "high": 4497.1,
    "close": 4496.8,
    "time": 1650532850601
  },
  {
    "low": 4496.7,
    "high": 4497,
    "close": 4496.7,
    "time": 1650532852317
  },
  {
    "low": 4497,
    "high": 4497,
    "close": 4497,
    "time": 1650532853941
  },
  {
    "low": 4496.8,
    "high": 4497.1,
    "close": 4497.1,
    "time": 1650532856116
  },
  {
    "low": 4496.8,
    "high": 4497.1,
    "close": 4497.1,
    "time": 1650532857578
  },
  {
    "low": 4496.9,
    "high": 4496.9,
    "close": 4496.9,
    "time": 1650532859813
  },
  {
    "low": 4496.9,
    "high": 4497.1,
    "close": 4496.9,
    "time": 1650532862417
  },
  {
    "low": 4496.9,
    "high": 4497,
    "close": 4497,
    "time": 1650532863930
  },
  {
    "low": 4497.1,
    "high": 4497.4,
    "close": 4497.4,
    "time": 1650532865295
  },
  {
    "low": 4497.1,
    "high": 4497.9,
    "close": 4497.4,
    "time": 1650532866380
  },
  {
    "low": 4497.3,
    "high": 4497.5,
    "close": 4497.5,
    "time": 1650532868395
  },
  {
    "low": 4497.3,
    "high": 4497.6,
    "close": 4497.5,
    "time": 1650532869571
  },
  {
    "low": 4497.3,
    "high": 4497.6,
    "close": 4497.4,
    "time": 1650532870939
  },
  {
    "low": 4497.3,
    "high": 4497.3,
    "close": 4497.3,
    "time": 1650532874130
  },
  {
    "low": 4497.3,
    "high": 4497.6,
    "close": 4497.4,
    "time": 1650532875202
  },
  {
    "low": 4497.3,
    "high": 4497.4,
    "close": 4497.3,
    "time": 1650532876242
  },
  {
    "low": 4497.3,
    "high": 4497.5,
    "close": 4497.5,
    "time": 1650532877975
  },
  {
    "low": 4497.3,
    "high": 4497.6,
    "close": 4497.3,
    "time": 1650532881088
  },
  {
    "low": 4497.5,
    "high": 4497.5,
    "close": 4497.5,
    "time": 1650532882371
  },
  {
    "low": 4497.3,
    "high": 4497.6,
    "close": 4497.4,
    "time": 1650532884975
  },
  {
    "low": 4497.3,
    "high": 4497.7,
    "close": 4497.4,
    "time": 1650532886220
  },
  {
    "low": 4497.3,
    "high": 4497.6,
    "close": 4497.4,
    "time": 1650532887933
  },
  {
    "low": 4497.3,
    "high": 4497.3,
    "close": 4497.3,
    "time": 1650532888950
  },
  {
    "low": 4497.4,
    "high": 4497.4,
    "close": 4497.4,
    "time": 1650532891455
  }
]