[
  {
    "timestamp": "2022-04-21T09:57:16.070Z",
    "bidQty": 477,
    "bid": 4493.4,
    "ofrQty": 477,
    "ofr": 4494.2,
    "_id": "62612a7cb7abb228586f2e5a"
  },
  {
    "timestamp": "2022-04-21T09:57:16.077Z",
    "bidQty": 477,
    "bid": 4493.5,
    "ofrQty": 477,
    "ofr": 4494.5,
    "_id": "62612a7cb7abb228586f2e5c"
  },
  {
    "timestamp": "2022-04-21T09:57:16.085Z",
    "bidQty": 477,
    "bid": 4493.5,
    "ofrQty": 477,
    "ofr": 4494.4,
    "_id": "62612a7cb7abb228586f2e5d"
  },
  {
    "timestamp": "2022-04-21T09:57:16.072Z",
    "bidQty": 477,
    "bid": 4493.2,
    "ofrQty": 477,
    "ofr": 4494.7,
    "_id": "62612a7cb7abb228586f2e5b"
  },
  {
    "timestamp": "2022-04-21T09:57:16.134Z",
    "bidQty": 477,
    "bid": 4493.1,
    "ofrQty": 477,
    "ofr": 4494.1,
    "_id": "62612a7cb7abb228586f2e60"
  },
  {
    "timestamp": "2022-04-21T09:57:16.094Z",
    "bidQty": 477,
    "bid": 4493.3,
    "ofrQty": 477,
    "ofr": 4494.2,
    "_id": "62612a7cb7abb228586f2e62"
  },
  {
    "timestamp": "2022-04-21T09:57:16.133Z",
    "bidQty": 477,
    "bid": 4493.2,
    "ofrQty": 477,
    "ofr": 4494.1,
    "_id": "62612a7cb7abb228586f2e5f"
  },
  {
    "timestamp": "2022-04-21T09:57:16.176Z",
    "bidQty": 477,
    "bid": 4493.1,
    "ofrQty": 477,
    "ofr": 4494.1,
    "_id": "62612a7cb7abb228586f2e63"
  },
  {
    "timestamp": "2022-04-21T09:57:16.085Z",
    "bidQty": 477,
    "bid": 4493.4,
    "ofrQty": 477,
    "ofr": 4494.4,
    "_id": "62612a7cb7abb228586f2e5e"
  },
  {
    "timestamp": "2022-04-21T09:57:16.137Z",
    "bidQty": 477,
    "bid": 4493.2,
    "ofrQty": 477,
    "ofr": 4494.1,
    "_id": "62612a7cb7abb228586f2e61"
  },
  {
    "timestamp": "2022-04-21T09:57:16.773Z",
    "bidQty": 477,
    "bid": 4493,
    "ofrQty": 477,
    "ofr": 4494.1,
    "_id": "62612a7cb7abb228586f2e64"
  },
  {
    "timestamp": "2022-04-21T09:57:16.798Z",
    "bidQty": 477,
    "bid": 4493.1,
    "ofrQty": 477,
    "ofr": 4494.1,
    "_id": "62612a7db7abb228586f2e65"
  },
  {
    "timestamp": "2022-04-21T09:57:20.157Z",
    "bidQty": 477,
    "bid": 4493.2,
    "ofrQty": 477,
    "ofr": 4494.1,
    "_id": "62612a80b7abb228586f2e66"
  },
  {
    "timestamp": "2022-04-21T09:57:20.554Z",
    "bidQty": 477,
    "bid": 4493.2,
    "ofrQty": 477,
    "ofr": 4494.2,
    "_id": "62612a80b7abb228586f2e67"
  },
  {
    "timestamp": "2022-04-21T09:57:20.765Z",
    "bidQty": 477,
    "bid": 4493.3,
    "ofrQty": 477,
    "ofr": 4494.2,
    "_id": "62612a80b7abb228586f2e68"
  },
  {
    "timestamp": "2022-04-21T09:57:23.553Z",
    "bidQty": 477,
    "bid": 4493.2,
    "ofrQty": 477,
    "ofr": 4494.2,
    "_id": "62612a83b7abb228586f2e69"
  },
  {
    "timestamp": "2022-04-21T09:57:25.203Z",
    "bidQty": 477,
    "bid": 4493.3,
    "ofrQty": 477,
    "ofr": 4494.2,
    "_id": "62612a85b7abb228586f2e6a"
  },
  {
    "timestamp": "2022-04-21T09:57:25.919Z",
    "bidQty": 477,
    "bid": 4493.3,
    "ofrQty": 477,
    "ofr": 4494.3,
    "_id": "62612a85b7abb228586f2e6b"
  },
  {
    "timestamp": "2022-04-21T09:57:30.039Z",
    "bidQty": 477,
    "bid": 4493.1,
    "ofrQty": 477,
    "ofr": 4494.6,
    "_id": "62612a8ab7abb228586f2e6c"
  },
  {
    "timestamp": "2022-04-21T09:57:30.095Z",
    "bidQty": 477,
    "bid": 4493.4,
    "ofrQty": 477,
    "ofr": 4494.4,
    "_id": "62612a8ab7abb228586f2e6d"
  },
  {
    "timestamp": "2022-04-21T09:57:30.159Z",
    "bidQty": 477,
    "bid": 4493.4,
    "ofrQty": 477,
    "ofr": 4494.3,
    "_id": "62612a8ab7abb228586f2e6e"
  },
  {
    "timestamp": "2022-04-21T09:57:30.165Z",
    "bidQty": 477,
    "bid": 4493.3,
    "ofrQty": 477,
    "ofr": 4494.3,
    "_id": "62612a8ab7abb228586f2e6f"
  },
  {
    "timestamp": "2022-04-21T09:57:30.522Z",
    "bidQty": 477,
    "bid": 4493,
    "ofrQty": 477,
    "ofr": 4494.5,
    "_id": "62612a8ab7abb228586f2e70"
  },
  {
    "timestamp": "2022-04-21T09:57:30.523Z",
    "bidQty": 477,
    "bid": 4493.2,
    "ofrQty": 477,
    "ofr": 4494.2,
    "_id": "62612a8ab7abb228586f2e71"
  },
  {
    "timestamp": "2022-04-21T09:57:33.922Z",
    "bidQty": 477,
    "bid": 4493.3,
    "ofrQty": 477,
    "ofr": 4494.2,
    "_id": "62612a8db7abb228586f2e72"
  },
  {
    "timestamp": "2022-04-21T09:57:33.922Z",
    "bidQty": 477,
    "bid": 4493.3,
    "ofrQty": 477,
    "ofr": 4494.3,
    "_id": "62612a8db7abb228586f2e73"
  },
  {
    "timestamp": "2022-04-21T09:57:34.226Z",
    "bidQty": 477,
    "bid": 4493.2,
    "ofrQty": 477,
    "ofr": 4494.2,
    "_id": "62612a8eb7abb228586f2e74"
  },
  {
    "timestamp": "2022-04-21T09:57:35.188Z",
    "bidQty": 477,
    "bid": 4493.1,
    "ofrQty": 477,
    "ofr": 4494.1,
    "_id": "62612a8fb7abb228586f2e75"
  },
  {
    "timestamp": "2022-04-21T09:57:35.201Z",
    "bidQty": 477,
    "bid": 4493,
    "ofrQty": 477,
    "ofr": 4494,
    "_id": "62612a8fb7abb228586f2e76"
  },
  {
    "timestamp": "2022-04-21T09:57:35.394Z",
    "bidQty": 477,
    "bid": 4493,
    "ofrQty": 477,
    "ofr": 4494.1,
    "_id": "62612a8fb7abb228586f2e77"
  },
  {
    "timestamp": "2022-04-21T09:57:35.395Z",
    "bidQty": 477,
    "bid": 4493.1,
    "ofrQty": 477,
    "ofr": 4494.1,
    "_id": "62612a8fb7abb228586f2e78"
  },
  {
    "timestamp": "2022-04-21T09:57:38.268Z",
    "bidQty": 477,
    "bid": 4493,
    "ofrQty": 477,
    "ofr": 4494,
    "_id": "62612a92b7abb228586f2e79"
  },
  {
    "timestamp": "2022-04-21T09:57:40.121Z",
    "bidQty": 477,
    "bid": 4492.8,
    "ofrQty": 477,
    "ofr": 4494.3,
    "_id": "62612a94b7abb228586f2e7a"
  },
  {
    "timestamp": "2022-04-21T09:57:41.803Z",
    "bidQty": 477,
    "bid": 4493.1,
    "ofrQty": 477,
    "ofr": 4494.1,
    "_id": "62612a95b7abb228586f2e7b"
  },
  {
    "timestamp": "2022-04-21T09:57:43.299Z",
    "bidQty": 477,
    "bid": 4492.8,
    "ofrQty": 477,
    "ofr": 4494.3,
    "_id": "62612a97b7abb228586f2e7c"
  },
  {
    "timestamp": "2022-04-21T09:57:43.302Z",
    "bidQty": 477,
    "bid": 4492.6,
    "ofrQty": 477,
    "ofr": 4494.1,
    "_id": "62612a97b7abb228586f2e7e"
  },
  {
    "timestamp": "2022-04-21T09:57:43.300Z",
    "bidQty": 477,
    "bid": 4493,
    "ofrQty": 477,
    "ofr": 4493.9,
    "_id": "62612a97b7abb228586f2e7d"
  },
  {
    "timestamp": "2022-04-21T09:57:43.305Z",
    "bidQty": 477,
    "bid": 4492.9,
    "ofrQty": 477,
    "ofr": 4493.9,
    "_id": "62612a97b7abb228586f2e7f"
  },
  {
    "timestamp": "2022-04-21T09:57:43.930Z",
    "bidQty": 477,
    "bid": 4492.7,
    "ofrQty": 477,
    "ofr": 4494.2,
    "_id": "62612a97b7abb228586f2e80"
  },
  {
    "timestamp": "2022-04-21T09:57:46.602Z",
    "bidQty": 477,
    "bid": 4493,
    "ofrQty": 477,
    "ofr": 4494,
    "_id": "62612a9ab7abb228586f2e81"
  },
  {
    "timestamp": "2022-04-21T09:57:46.679Z",
    "bidQty": 477,
    "bid": 4492.8,
    "ofrQty": 477,
    "ofr": 4494.3,
    "_id": "62612a9ab7abb228586f2e82"
  },
  {
    "timestamp": "2022-04-21T09:57:48.003Z",
    "bidQty": 477,
    "bid": 4493,
    "ofrQty": 477,
    "ofr": 4494,
    "_id": "62612a9cb7abb228586f2e83"
  },
  {
    "timestamp": "2022-04-21T09:57:48.010Z",
    "bidQty": 477,
    "bid": 4492.7,
    "ofrQty": 477,
    "ofr": 4494.2,
    "_id": "62612a9cb7abb228586f2e84"
  },
  {
    "timestamp": "2022-04-21T09:57:48.318Z",
    "bidQty": 477,
    "bid": 4493,
    "ofrQty": 477,
    "ofr": 4494,
    "_id": "62612a9cb7abb228586f2e85"
  },
  {
    "timestamp": "2022-04-21T09:57:52.459Z",
    "bidQty": 477,
    "bid": 4493,
    "ofrQty": 477,
    "ofr": 4494.1,
    "_id": "62612aa0b7abb228586f2e86"
  },
  {
    "timestamp": "2022-04-21T09:57:52.460Z",
    "bidQty": 477,
    "bid": 4493.1,
    "ofrQty": 477,
    "ofr": 4494.1,
    "_id": "62612aa0b7abb228586f2e87"
  },
  {
    "timestamp": "2022-04-21T09:57:53.099Z",
    "bidQty": 477,
    "bid": 4493.2,
    "ofrQty": 477,
    "ofr": 4494.1,
    "_id": "62612aa1b7abb228586f2e88"
  },
  {
    "timestamp": "2022-04-21T09:57:53.140Z",
    "bidQty": 477,
    "bid": 4493.2,
    "ofrQty": 477,
    "ofr": 4494.2,
    "_id": "62612aa1b7abb228586f2e89"
  },
  {
    "timestamp": "2022-04-21T09:57:53.349Z",
    "bidQty": 477,
    "bid": 4493.3,
    "ofrQty": 477,
    "ofr": 4494.3,
    "_id": "62612aa1b7abb228586f2e8b"
  },
  {
    "timestamp": "2022-04-21T09:57:53.347Z",
    "bidQty": 477,
    "bid": 4493.3,
    "ofrQty": 477,
    "ofr": 4494.2,
    "_id": "62612aa1b7abb228586f2e8a"
  },
  {
    "timestamp": "2022-04-21T09:57:53.544Z",
    "bidQty": 477,
    "bid": 4493.3,
    "ofrQty": 477,
    "ofr": 4494.2,
    "_id": "62612aa1b7abb228586f2e8c"
  },
  {
    "timestamp": "2022-04-21T09:57:53.544Z",
    "bidQty": 477,
    "bid": 4493.3,
    "ofrQty": 477,
    "ofr": 4494.3,
    "_id": "62612aa1b7abb228586f2e8d"
  },
  {
    "timestamp": "2022-04-21T09:57:53.774Z",
    "bidQty": 477,
    "bid": 4493.4,
    "ofrQty": 477,
    "ofr": 4494.3,
    "_id": "62612aa1b7abb228586f2e8e"
  },
  {
    "timestamp": "2022-04-21T09:57:53.836Z",
    "bidQty": 477,
    "bid": 4493.4,
    "ofrQty": 477,
    "ofr": 4494.4,
    "_id": "62612aa1b7abb228586f2e8f"
  },
  {
    "timestamp": "2022-04-21T09:57:54.337Z",
    "bidQty": 477,
    "bid": 4493.3,
    "ofrQty": 477,
    "ofr": 4494.3,
    "_id": "62612aa2b7abb228586f2e90"
  },
  {
    "timestamp": "2022-04-21T09:57:55.493Z",
    "bidQty": 477,
    "bid": 4493.4,
    "ofrQty": 477,
    "ofr": 4494.3,
    "_id": "62612aa3b7abb228586f2e91"
  },
  {
    "timestamp": "2022-04-21T09:57:56.060Z",
    "bidQty": 477,
    "bid": 4493.4,
    "ofrQty": 477,
    "ofr": 4494.4,
    "_id": "62612aa4b7abb228586f2e92"
  },
  {
    "timestamp": "2022-04-21T09:57:56.065Z",
    "bidQty": 477,
    "bid": 4493.5,
    "ofrQty": 477,
    "ofr": 4494.4,
    "_id": "62612aa4b7abb228586f2e93"
  },
  {
    "timestamp": "2022-04-21T09:57:56.091Z",
    "bidQty": 477,
    "bid": 4493.4,
    "ofrQty": 477,
    "ofr": 4494.4,
    "_id": "62612aa4b7abb228586f2e94"
  },
  {
    "timestamp": "2022-04-21T09:57:57.063Z",
    "bidQty": 477,
    "bid": 4493.5,
    "ofrQty": 477,
    "ofr": 4494.4,
    "_id": "62612aa5b7abb228586f2e95"
  },
  {
    "timestamp": "2022-04-21T09:58:00.319Z",
    "bidQty": 477,
    "bid": 4493.5,
    "ofrQty": 477,
    "ofr": 4494.5,
    "_id": "62612aa8b7abb228586f2e96"
  },
  {
    "timestamp": "2022-04-21T09:58:01.400Z",
    "bidQty": 477,
    "bid": 4493.5,
    "ofrQty": 477,
    "ofr": 4494.6,
    "_id": "62612aa9b7abb228586f2e97"
  },
  {
    "timestamp": "2022-04-21T09:58:01.404Z",
    "bidQty": 477,
    "bid": 4493.5,
    "ofrQty": 477,
    "ofr": 4494.5,
    "_id": "62612aa9b7abb228586f2e98"
  },
  {
    "timestamp": "2022-04-21T09:58:01.464Z",
    "bidQty": 477,
    "bid": 4493.5,
    "ofrQty": 477,
    "ofr": 4494.4,
    "_id": "62612aa9b7abb228586f2e99"
  },
  {
    "timestamp": "2022-04-21T09:58:01.476Z",
    "bidQty": 477,
    "bid": 4493.4,
    "ofrQty": 477,
    "ofr": 4494.4,
    "_id": "62612aa9b7abb228586f2e9a"
  },
  {
    "timestamp": "2022-04-21T09:58:01.493Z",
    "bidQty": 477,
    "bid": 4493.5,
    "ofrQty": 477,
    "ofr": 4494.4,
    "_id": "62612aa9b7abb228586f2e9b"
  },
  {
    "timestamp": "2022-04-21T09:58:01.502Z",
    "bidQty": 477,
    "bid": 4493.4,
    "ofrQty": 477,
    "ofr": 4494.4,
    "_id": "62612aa9b7abb228586f2e9c"
  },
  {
    "timestamp": "2022-04-21T09:58:01.777Z",
    "bidQty": 477,
    "bid": 4493.5,
    "ofrQty": 477,
    "ofr": 4494.4,
    "_id": "62612aa9b7abb228586f2e9d"
  },
  {
    "timestamp": "2022-04-21T09:58:02.077Z",
    "bidQty": 477,
    "bid": 4493.5,
    "ofrQty": 477,
    "ofr": 4494.5,
    "_id": "62612aaab7abb228586f2e9e"
  },
  {
    "timestamp": "2022-04-21T09:58:02.861Z",
    "bidQty": 477,
    "bid": 4493.5,
    "ofrQty": 477,
    "ofr": 4494.4,
    "_id": "62612aaab7abb228586f2e9f"
  }
]
