[
  {
    "timestamp": "2022-04-21T10:16:55.825Z",
    "bid": 4494.4,
    "ofr": 4495.4,
    "ofrQty": 477,
    "_id": "62612f18b7abb228586f35f1",
    "bidQty": 477
  },
  {
    "timestamp": "2022-04-21T10:16:57.327Z",
    "bid": 4494.5,
    "ofr": 4495.4,
    "ofrQty": 477,
    "_id": "62612f1ab7abb228586f35f2",
    "bidQty": 477
  },
  {
    "timestamp": "2022-04-21T10:16:57.329Z",
    "bid": 4494.4,
    "ofr": 4495.4,
    "ofrQty": 477,
    "_id": "62612f1ab7abb228586f35f3",
    "bidQty": 477
  },
  {
    "timestamp": "2022-04-21T10:16:58.080Z",
    "bid": 4494.5,
    "ofr": 4495.4,
    "ofrQty": 477,
    "_id": "62612f1ab7abb228586f35f4",
    "bidQty": 477
  },
  {
    "timestamp": "2022-04-21T10:16:59.726Z",
    "bid": 4494.4,
    "ofr": 4495.4,
    "ofrQty": 477,
    "_id": "62612f1bb7abb228586f35f5",
    "bidQty": 477
  },
  {
    "timestamp": "2022-04-21T10:16:59.798Z",
    "bid": 4494.5,
    "ofr": 4495.4,
    "ofrQty": 477,
    "_id": "62612f1bb7abb228586f35f6",
    "bidQty": 477
  },
  {
    "timestamp": "2022-04-21T10:16:59.973Z",
    "bid": 4494.4,
    "ofr": 4495.4,
    "ofrQty": 477,
    "_id": "62612f1cb7abb228586f35f7",
    "bidQty": 477
  },
  {
    "timestamp": "2022-04-21T10:17:01.596Z",
    "bid": 4494.2,
    "ofr": 4495.7,
    "ofrQty": 477,
    "_id": "62612f1db7abb228586f35f8",
    "bidQty": 477
  },
  {
    "timestamp": "2022-04-21T10:17:01.599Z",
    "bid": 4494.7,
    "ofr": 4495.5,
    "ofrQty": 477,
    "_id": "62612f1db7abb228586f35fa",
    "bidQty": 477
  },
  {
    "timestamp": "2022-04-21T10:17:01.599Z",
    "bid": 4494.5,
    "ofr": 4495.6,
    "ofrQty": 477,
    "_id": "62612f1db7abb228586f35f9",
    "bidQty": 477
  },
  {
    "timestamp": "2022-04-21T10:17:01.608Z",
    "bid": 4494.7,
    "ofr": 4495.7,
    "ofrQty": 477,
    "_id": "62612f1db7abb228586f35fb",
    "bidQty": 477
  },
  {
    "timestamp": "2022-04-21T10:17:01.655Z",
    "bid": 4494.7,
    "ofr": 4495.6,
    "ofrQty": 477,
    "_id": "62612f1db7abb228586f35fc",
    "bidQty": 477
  },
  {
    "timestamp": "2022-04-21T10:17:01.655Z",
    "bid": 4494.6,
    "ofr": 4495.6,
    "ofrQty": 477,
    "_id": "62612f1db7abb228586f35fd",
    "bidQty": 477
  },
  {
    "timestamp": "2022-04-21T10:17:01.666Z",
    "bid": 4494.4,
    "ofr": 4495.9,
    "ofrQty": 477,
    "_id": "62612f1db7abb228586f35fe",
    "bidQty": 477
  },
  {
    "timestamp": "2022-04-21T10:17:01.671Z",
    "bid": 4494.7,
    "ofr": 4495.7,
    "ofrQty": 477,
    "_id": "62612f1db7abb228586f35ff",
    "bidQty": 477
  },
  {
    "timestamp": "2022-04-21T10:17:01.721Z",
    "bid": 4494.4,
    "ofr": 4495.9,
    "ofrQty": 477,
    "_id": "62612f1db7abb228586f3600",
    "bidQty": 477
  },
  {
    "timestamp": "2022-04-21T10:17:01.721Z",
    "bid": 4494.6,
    "ofr": 4495.6,
    "ofrQty": 477,
    "_id": "62612f1db7abb228586f3601",
    "bidQty": 477
  },
  {
    "timestamp": "2022-04-21T10:17:03.305Z",
    "bid": 4494.7,
    "ofr": 4495.7,
    "ofrQty": 477,
    "_id": "62612f1fb7abb228586f3603",
    "bidQty": 477
  },
  {
    "timestamp": "2022-04-21T10:17:03.314Z",
    "bid": 4494.5,
    "ofr": 4496,
    "ofrQty": 477,
    "_id": "62612f1fb7abb228586f3604",
    "bidQty": 477
  },
  {
    "timestamp": "2022-04-21T10:17:03.302Z",
    "bid": 4494.4,
    "ofr": 4495.9,
    "ofrQty": 477,
    "_id": "62612f1fb7abb228586f3602",
    "bidQty": 477
  },
  {
    "timestamp": "2022-04-21T10:17:04.374Z",
    "bid": 4494.6,
    "ofr": 4496.1,
    "ofrQty": 477,
    "_id": "62612f20b7abb228586f3605",
    "bidQty": 477
  },
  {
    "timestamp": "2022-04-21T10:17:04.374Z",
    "bid": 4494.8,
    "ofr": 4495.8,
    "ofrQty": 477,
    "_id": "62612f20b7abb228586f3606",
    "bidQty": 477
  },
  {
    "timestamp": "2022-04-21T10:17:04.428Z",
    "bid": 4494.9,
    "ofr": 4495.9,
    "ofrQty": 477,
    "_id": "62612f20b7abb228586f3607",
    "bidQty": 477
  },
  {
    "timestamp": "2022-04-21T10:17:05.012Z",
    "bid": 4494.9,
    "ofr": 4495.8,
    "ofrQty": 477,
    "_id": "62612f21b7abb228586f3608",
    "bidQty": 477
  },
  {
    "timestamp": "2022-04-21T10:17:05.012Z",
    "bid": 4494.8,
    "ofr": 4495.8,
    "ofrQty": 477,
    "_id": "62612f21b7abb228586f3609",
    "bidQty": 477
  },
  {
    "timestamp": "2022-04-21T10:17:06.444Z",
    "bid": 4494.6,
    "ofr": 4496.1,
    "ofrQty": 477,
    "_id": "62612f22b7abb228586f360a",
    "bidQty": 477
  },
  {
    "timestamp": "2022-04-21T10:17:06.496Z",
    "bid": 4494.9,
    "ofr": 4495.9,
    "ofrQty": 477,
    "_id": "62612f22b7abb228586f360b",
    "bidQty": 477
  },
  {
    "timestamp": "2022-04-21T10:17:06.904Z",
    "bid": 4494.6,
    "ofr": 4496.1,
    "ofrQty": 477,
    "_id": "62612f22b7abb228586f360c",
    "bidQty": 477
  },
  {
    "timestamp": "2022-04-21T10:17:07.186Z",
    "bid": 4494.9,
    "ofr": 4495.9,
    "ofrQty": 477,
    "_id": "62612f23b7abb228586f360d",
    "bidQty": 477
  },
  {
    "timestamp": "2022-04-21T10:17:07.333Z",
    "bid": 4494.6,
    "ofr": 4496.1,
    "ofrQty": 477,
    "_id": "62612f23b7abb228586f360e",
    "bidQty": 477
  },
  {
    "timestamp": "2022-04-21T10:17:07.739Z",
    "bid": 4495,
    "ofr": 4496,
    "ofrQty": 477,
    "_id": "62612f23b7abb228586f360f",
    "bidQty": 477
  },
  {
    "timestamp": "2022-04-21T10:17:07.738Z",
    "bid": 4494.7,
    "ofr": 4496.2,
    "ofrQty": 477,
    "_id": "62612f23b7abb228586f3610",
    "bidQty": 477
  },
  {
    "timestamp": "2022-04-21T10:17:07.738Z",
    "bid": 4494.9,
    "ofr": 4495.9,
    "ofrQty": 477,
    "_id": "62612f23b7abb228586f3611",
    "bidQty": 477
  },
  {
    "timestamp": "2022-04-21T10:17:12.673Z",
    "bid": 4495,
    "ofr": 4495.9,
    "ofrQty": 477,
    "_id": "62612f28b7abb228586f3612",
    "bidQty": 477
  },
  {
    "timestamp": "2022-04-21T10:17:13.761Z",
    "bid": 4494.9,
    "ofr": 4495.9,
    "ofrQty": 477,
    "_id": "62612f29b7abb228586f3613",
    "bidQty": 477
  },
  {
    "timestamp": "2022-04-21T10:17:14.096Z",
    "bid": 4495,
    "ofr": 4495.9,
    "ofrQty": 477,
    "_id": "62612f2ab7abb228586f3614",
    "bidQty": 477
  },
  {
    "timestamp": "2022-04-21T10:17:14.770Z",
    "bid": 4495,
    "ofr": 4496,
    "ofrQty": 477,
    "_id": "62612f2ab7abb228586f3615",
    "bidQty": 477
  },
  {
    "timestamp": "2022-04-21T10:17:14.819Z",
    "bid": 4494.8,
    "ofr": 4496.3,
    "ofrQty": 477,
    "_id": "62612f2ab7abb228586f3616",
    "bidQty": 477
  },
  {
    "timestamp": "2022-04-21T10:17:14.821Z",
    "bid": 4495,
    "ofr": 4496,
    "ofrQty": 477,
    "_id": "62612f2ab7abb228586f3617",
    "bidQty": 477
  },
  {
    "timestamp": "2022-04-21T10:17:15.790Z",
    "bid": 4494.8,
    "ofr": 4496.3,
    "ofrQty": 477,
    "_id": "62612f2bb7abb228586f3618",
    "bidQty": 477
  },
  {
    "timestamp": "2022-04-21T10:17:15.791Z",
    "bid": 4494.9,
    "ofr": 4496.4,
    "ofrQty": 477,
    "_id": "62612f2bb7abb228586f3619",
    "bidQty": 477
  },
  {
    "timestamp": "2022-04-21T10:17:15.793Z",
    "bid": 4495.2,
    "ofr": 4496.2,
    "ofrQty": 477,
    "_id": "62612f2bb7abb228586f361a",
    "bidQty": 477
  },
  {
    "timestamp": "2022-04-21T10:17:18.385Z",
    "bid": 4495.2,
    "ofr": 4496.1,
    "ofrQty": 477,
    "_id": "62612f2eb7abb228586f361b",
    "bidQty": 477
  }
]
