[
  {
    "low": 4496.8,
    "high": 4496.8,
    "close": 4496.8,
    "time": 1650536929183
  },
  {
    "low": 4496.9,
    "high": 4496.9,
    "close": 4496.9,
    "time": 1650536932570
  },
  {
    "low": 4496.8,
    "high": 4496.8,
    "close": 4496.8,
    "time": 1650536935608
  },
  {
    "low": 4496.7,
    "high": 4497,
    "close": 4496.8,
    "time": 1650536937271
  },
  {
    "low": 4496.8,
    "high": 4497,
    "close": 4497,
    "time": 1650536939516
  },
  {
    "low": 4496.9,
    "high": 4497,
    "close": 4497,
    "time": 1650536940846
  },
  {
    "low": 4497.1,
    "high": 4497.1,
    "close": 4497.1,
    "time": 1650536941990
  },
  {
    "low": 4497.1,
    "high": 4497.3,
    "close": 4497.3,
    "time": 1650536944426
  },
  {
    "low": 4497.2,
    "high": 4497.3,
    "close": 4497.3,
    "time": 1650536946087
  },
  {
    "low": 4497.1,
    "high": 4497.5,
    "close": 4497.1,
    "time": 1650536948687
  },
  {
    "low": 4497.2,
    "high": 4497.2,
    "close": 4497.2,
    "time": 1650536949940
  },
  {
    "low": 4497.2,
    "high": 4497.5,
    "close": 4497.3,
    "time": 1650536953539
  },
  {
    "low": 4497.3,
    "high": 4497.4,
    "close": 4497.3,
    "time": 1650536954717
  },
  {
    "low": 4497.3,
    "high": 4497.4,
    "close": 4497.4,
    "time": 1650536955946
  },
  {
    "low": 4497.4,
    "high": 4497.6,
    "close": 4497.4,
    "time": 1650536958941
  },
  {
    "low": 4497.5,
    "high": 4497.6,
    "close": 4497.5,
    "time": 1650536960650
  },
  {
    "low": 4497.5,
    "high": 4497.6,
    "close": 4497.5,
    "time": 1650536964998
  },
  {
    "low": 4497.4,
    "high": 4497.6,
    "close": 4497.5,
    "time": 1650536967127
  },
  {
    "low": 4497.5,
    "high": 4497.6,
    "close": 4497.5,
    "time": 1650536968413
  },
  {
    "low": 4497.5,
    "high": 4497.6,
    "close": 4497.5,
    "time": 1650536969458
  },
  {
    "low": 4497.4,
    "high": 4497.6,
    "close": 4497.6,
    "time": 1650536970796
  },
  {
    "low": 4497.5,
    "high": 4497.6,
    "close": 4497.6,
    "time": 1650536971966
  },
  {
    "low": 4497.5,
    "high": 4497.6,
    "close": 4497.6,
    "time": 1650536974413
  },
  {
    "low": 4497.5,
    "high": 4497.5,
    "close": 4497.5,
    "time": 1650536975471
  },
  {
    "low": 4497.6,
    "high": 4497.6,
    "close": 4497.6,
    "time": 1650536976866
  },
  {
    "low": 4497.6,
    "high": 4497.6,
    "close": 4497.6,
    "time": 1650536978776
  },
  {
    "low": 4497.5,
    "high": 4497.6,
    "close": 4497.5,
    "time": 1650536979832
  },
  {
    "low": 4497.6,
    "high": 4497.7,
    "close": 4497.7,
    "time": 1650536982043
  },
  {
    "low": 4497.5,
    "high": 4497.6,
    "close": 4497.6,
    "time": 1650536984004
  },
  {
    "low": 4497.6,
    "high": 4497.6,
    "close": 4497.6,
    "time": 1650536985912
  },
  {
    "low": 4497.6,
    "high": 4497.6,
    "close": 4497.6,
    "time": 1650536987777
  },
  {
    "low": 4497.6,
    "high": 4497.7,
    "close": 4497.7,
    "time": 1650536991377
  },
  {
    "low": 4497.6,
    "high": 4497.6,
    "close": 4497.6,
    "time": 1650536993727
  },
  {
    "low": 4497.6,
    "high": 4497.6,
    "close": 4497.6,
    "time": 1650536995134
  },
  {
    "low": 4497.5,
    "high": 4497.6,
    "close": 4497.6,
    "time": 1650536996188
  },
  {
    "low": 4497.6,
    "high": 4497.6,
    "close": 4497.6,
    "time": 1650536997320
  },
  {
    "low": 4497.5,
    "high": 4497.6,
    "close": 4497.5,
    "time": 1650536999090
  },
  {
    "low": 4497.6,
    "high": 4497.7,
    "close": 4497.7,
    "time": 1650537000418
  },
  {
    "low": 4497.6,
    "high": 4497.8,
    "close": 4497.8,
    "time": 1650537001646
  },
  {
    "low": 4497.8,
    "high": 4498,
    "close": 4498,
    "time": 1650537003297
  },
  {
    "low": 4498.1,
    "high": 4498.1,
    "close": 4498.1,
    "time": 1650537005715
  },
  {
    "low": 4498,
    "high": 4498.1,
    "close": 4498,
    "time": 1650537008741
  },
  {
    "low": 4497.7,
    "high": 4498,
    "close": 4497.8,
    "time": 1650537012203
  },
  {
    "low": 4497.8,
    "high": 4497.9,
    "close": 4497.8,
    "time": 1650537014730
  },
  {
    "low": 4497.8,
    "high": 4498,
    "close": 4498,
    "time": 1650537017077
  }
]