[
  {
    "timestamp": "2022-04-21T11:03:17.470Z",
    "bid": 4497,
    "ofrQty": 477,
    "bidQty": 477,
    "_id": "626139f5b7abb228586f448b",
    "ofr": 4498
  },
  {
    "timestamp": "2022-04-21T11:03:17.654Z",
    "bid": 4497,
    "ofrQty": 477,
    "bidQty": 477,
    "_id": "626139f5b7abb228586f448c",
    "ofr": 4497.9
  },
  {
    "timestamp": "2022-04-21T11:03:17.667Z",
    "bid": 4497,
    "ofrQty": 477,
    "bidQty": 477,
    "_id": "626139f5b7abb228586f448d",
    "ofr": 4498
  },
  {
    "timestamp": "2022-04-21T11:03:18.570Z",
    "bid": 4497,
    "ofrQty": 477,
    "bidQty": 477,
    "_id": "626139f6b7abb228586f448e",
    "ofr": 4498.1
  },
  {
    "timestamp": "2022-04-21T11:03:18.573Z",
    "bid": 4497.2,
    "ofrQty": 477,
    "bidQty": 477,
    "_id": "626139f6b7abb228586f448f",
    "ofr": 4498.1
  },
  {
    "timestamp": "2022-04-21T11:03:18.579Z",
    "bid": 4496.9,
    "ofrQty": 477,
    "bidQty": 477,
    "_id": "626139f6b7abb228586f4490",
    "ofr": 4498.8
  },
  {
    "timestamp": "2022-04-21T11:03:18.576Z",
    "bid": 4497.2,
    "ofrQty": 477,
    "bidQty": 477,
    "_id": "626139f6b7abb228586f4491",
    "ofr": 4498.2
  },
  {
    "timestamp": "2022-04-21T11:03:18.580Z",
    "bid": 4497.2,
    "ofrQty": 477,
    "bidQty": 477,
    "_id": "626139f6b7abb228586f4492",
    "ofr": 4498.2
  },
  {
    "timestamp": "2022-04-21T11:03:19.111Z",
    "bid": 4497.2,
    "ofrQty": 477,
    "bidQty": 477,
    "_id": "626139f7b7abb228586f4493",
    "ofr": 4498.1
  },
  {
    "timestamp": "2022-04-21T11:03:21.594Z",
    "bid": 4497.2,
    "ofrQty": 477,
    "bidQty": 477,
    "_id": "626139f9b7abb228586f4494",
    "ofr": 4498.2
  },
  {
    "timestamp": "2022-04-21T11:03:21.638Z",
    "bid": 4497.2,
    "ofrQty": 477,
    "bidQty": 477,
    "_id": "626139f9b7abb228586f4495",
    "ofr": 4498.1
  },
  {
    "timestamp": "2022-04-21T11:03:24.008Z",
    "bid": 4497.2,
    "ofrQty": 477,
    "bidQty": 477,
    "_id": "626139fcb7abb228586f4496",
    "ofr": 4498.2
  },
  {
    "timestamp": "2022-04-21T11:03:24.009Z",
    "bid": 4497.2,
    "ofrQty": 477,
    "bidQty": 477,
    "_id": "626139fcb7abb228586f4497",
    "ofr": 4498.1
  },
  {
    "timestamp": "2022-04-21T11:03:24.919Z",
    "bid": 4497.2,
    "ofrQty": 477,
    "bidQty": 477,
    "_id": "626139fcb7abb228586f4498",
    "ofr": 4498.2
  },
  {
    "timestamp": "2022-04-21T11:03:24.922Z",
    "bid": 4497.3,
    "ofrQty": 477,
    "bidQty": 477,
    "_id": "626139fcb7abb228586f4499",
    "ofr": 4498.2
  },
  {
    "timestamp": "2022-04-21T11:03:24.929Z",
    "bid": 4497.1,
    "ofrQty": 477,
    "bidQty": 477,
    "_id": "626139fcb7abb228586f449a",
    "ofr": 4498.6
  },
  {
    "timestamp": "2022-04-21T11:03:24.930Z",
    "bid": 4496.9,
    "ofrQty": 477,
    "bidQty": 477,
    "_id": "626139fcb7abb228586f449b",
    "ofr": 4498.9
  },
  {
    "timestamp": "2022-04-21T11:03:24.930Z",
    "bid": 4497.4,
    "ofrQty": 477,
    "bidQty": 477,
    "_id": "626139fcb7abb228586f449c",
    "ofr": 4498.3
  },
  {
    "timestamp": "2022-04-21T11:03:24.931Z",
    "bid": 4497.2,
    "ofrQty": 477,
    "bidQty": 477,
    "_id": "626139fcb7abb228586f449d",
    "ofr": 4498.7
  },
  {
    "timestamp": "2022-04-21T11:03:24.933Z",
    "bid": 4497.5,
    "ofrQty": 477,
    "bidQty": 477,
    "_id": "626139fdb7abb228586f449f",
    "ofr": 4498.4
  },
  {
    "timestamp": "2022-04-21T11:03:24.931Z",
    "bid": 4497.5,
    "ofrQty": 477,
    "bidQty": 477,
    "_id": "626139fcb7abb228586f449e",
    "ofr": 4498.5
  },
  {
    "timestamp": "2022-04-21T11:03:26.426Z",
    "bid": 4497.5,
    "ofrQty": 477,
    "bidQty": 477,
    "_id": "626139feb7abb228586f44a0",
    "ofr": 4498.3
  },
  {
    "timestamp": "2022-04-21T11:03:26.429Z",
    "bid": 4497.4,
    "ofrQty": 477,
    "bidQty": 477,
    "_id": "626139feb7abb228586f44a1",
    "ofr": 4498.3
  },
  {
    "timestamp": "2022-04-21T11:03:26.500Z",
    "bid": 4497.4,
    "ofrQty": 477,
    "bidQty": 477,
    "_id": "626139feb7abb228586f44a2",
    "ofr": 4498.2
  },
  {
    "timestamp": "2022-04-21T11:03:26.501Z",
    "bid": 4497.2,
    "ofrQty": 477,
    "bidQty": 477,
    "_id": "626139feb7abb228586f44a3",
    "ofr": 4498.2
  },
  {
    "timestamp": "2022-04-21T11:03:26.573Z",
    "bid": 4497.2,
    "ofrQty": 477,
    "bidQty": 477,
    "_id": "626139feb7abb228586f44a4",
    "ofr": 4498.1
  },
  {
    "timestamp": "2022-04-21T11:03:28.789Z",
    "bid": 4497.2,
    "ofrQty": 477,
    "bidQty": 477,
    "_id": "62613a00b7abb228586f44a6",
    "ofr": 4498
  },
  {
    "timestamp": "2022-04-21T11:03:28.794Z",
    "bid": 4497,
    "ofrQty": 477,
    "bidQty": 477,
    "_id": "62613a00b7abb228586f44a7",
    "ofr": 4497.8
  },
  {
    "timestamp": "2022-04-21T11:03:28.792Z",
    "bid": 4497.1,
    "ofrQty": 477,
    "bidQty": 477,
    "_id": "62613a00b7abb228586f44a8",
    "ofr": 4498
  },
  {
    "timestamp": "2022-04-21T11:03:28.793Z",
    "bid": 4497.1,
    "ofrQty": 477,
    "bidQty": 477,
    "_id": "62613a00b7abb228586f44a5",
    "ofr": 4497.9
  },
  {
    "timestamp": "2022-04-21T11:03:28.803Z",
    "bid": 4496.5,
    "ofrQty": 477,
    "bidQty": 477,
    "_id": "62613a00b7abb228586f44a9",
    "ofr": 4498
  },
  {
    "timestamp": "2022-04-21T11:03:28.812Z",
    "bid": 4496.9,
    "ofrQty": 477,
    "bidQty": 477,
    "_id": "62613a00b7abb228586f44aa",
    "ofr": 4497.8
  },
  {
    "timestamp": "2022-04-21T11:03:28.969Z",
    "bid": 4496.8,
    "ofrQty": 477,
    "bidQty": 477,
    "_id": "62613a01b7abb228586f44ab",
    "ofr": 4497.8
  },
  {
    "timestamp": "2022-04-21T11:03:28.970Z",
    "bid": 4496.9,
    "ofrQty": 477,
    "bidQty": 477,
    "_id": "62613a01b7abb228586f44ac",
    "ofr": 4497.8
  },
  {
    "timestamp": "2022-04-21T11:03:29.550Z",
    "bid": 4496.9,
    "ofrQty": 477,
    "bidQty": 477,
    "_id": "62613a01b7abb228586f44ad",
    "ofr": 4497.9
  },
  {
    "timestamp": "2022-04-21T11:03:30.989Z",
    "bid": 4496.9,
    "ofrQty": 477,
    "bidQty": 477,
    "_id": "62613a03b7abb228586f44ae",
    "ofr": 4497.8
  },
  {
    "timestamp": "2022-04-21T11:03:31.829Z",
    "bid": 4496.8,
    "ofrQty": 477,
    "bidQty": 477,
    "_id": "62613a03b7abb228586f44af",
    "ofr": 4497.8
  },
  {
    "timestamp": "2022-04-21T11:03:31.833Z",
    "bid": 4496.8,
    "ofrQty": 477,
    "bidQty": 477,
    "_id": "62613a03b7abb228586f44b0",
    "ofr": 4497.7
  },
  {
    "timestamp": "2022-04-21T11:03:32.634Z",
    "bid": 4496.8,
    "ofrQty": 477,
    "bidQty": 477,
    "_id": "62613a04b7abb228586f44b1",
    "ofr": 4497.8
  },
  {
    "timestamp": "2022-04-21T11:03:34.141Z",
    "bid": 4496.8,
    "ofrQty": 477,
    "bidQty": 477,
    "_id": "62613a06b7abb228586f44b2",
    "ofr": 4497.7
  },
  {
    "timestamp": "2022-04-21T11:03:34.157Z",
    "bid": 4496.7,
    "ofrQty": 477,
    "bidQty": 477,
    "_id": "62613a06b7abb228586f44b3",
    "ofr": 4497.7
  },
  {
    "timestamp": "2022-04-21T11:03:36.243Z",
    "bid": 4496.6,
    "ofrQty": 477,
    "bidQty": 477,
    "_id": "62613a08b7abb228586f44b4",
    "ofr": 4497.6
  },
  {
    "timestamp": "2022-04-21T11:03:37.231Z",
    "bid": 4496.7,
    "ofrQty": 477,
    "bidQty": 477,
    "_id": "62613a09b7abb228586f44b5",
    "ofr": 4497.6
  },
  {
    "timestamp": "2022-04-21T11:03:37.302Z",
    "bid": 4496.7,
    "ofrQty": 477,
    "bidQty": 477,
    "_id": "62613a09b7abb228586f44b6",
    "ofr": 4497.7
  },
  {
    "timestamp": "2022-04-21T11:03:38.304Z",
    "bid": 4496.8,
    "ofrQty": 477,
    "bidQty": 477,
    "_id": "62613a0ab7abb228586f44b7",
    "ofr": 4497.7
  },
  {
    "timestamp": "2022-04-21T11:03:38.379Z",
    "bid": 4496.8,
    "ofrQty": 477,
    "bidQty": 477,
    "_id": "62613a0ab7abb228586f44b8",
    "ofr": 4497.8
  },
  {
    "timestamp": "2022-04-21T11:03:40.327Z",
    "bid": 4496.8,
    "ofrQty": 477,
    "bidQty": 477,
    "_id": "62613a0cb7abb228586f44b9",
    "ofr": 4497.7
  },
  {
    "timestamp": "2022-04-21T11:03:40.677Z",
    "bid": 4496.7,
    "ofrQty": 477,
    "bidQty": 477,
    "_id": "62613a0cb7abb228586f44ba",
    "ofr": 4497.7
  },
  {
    "timestamp": "2022-04-21T11:03:42.773Z",
    "bid": 4496.8,
    "ofrQty": 477,
    "bidQty": 477,
    "_id": "62613a0eb7abb228586f44bb",
    "ofr": 4497.7
  },
  {
    "timestamp": "2022-04-21T11:03:42.807Z",
    "bid": 4496.8,
    "ofrQty": 477,
    "bidQty": 477,
    "_id": "62613a0eb7abb228586f44bc",
    "ofr": 4497.8
  },
  {
    "timestamp": "2022-04-21T11:03:43.876Z",
    "bid": 4496.7,
    "ofrQty": 477,
    "bidQty": 477,
    "_id": "62613a0fb7abb228586f44bd",
    "ofr": 4497.7
  },
  {
    "timestamp": "2022-04-21T11:03:45.851Z",
    "bid": 4496.6,
    "ofrQty": 477,
    "bidQty": 477,
    "_id": "62613a11b7abb228586f44be",
    "ofr": 4497.6
  },
  {
    "timestamp": "2022-04-21T11:03:48.183Z",
    "bid": 4496.7,
    "ofrQty": 477,
    "bidQty": 477,
    "_id": "62613a14b7abb228586f44bf",
    "ofr": 4497.6
  },
  {
    "timestamp": "2022-04-21T11:03:48.389Z",
    "bid": 4496.6,
    "ofrQty": 477,
    "bidQty": 477,
    "_id": "62613a14b7abb228586f44c0",
    "ofr": 4497.6
  },
  {
    "timestamp": "2022-04-21T11:03:48.954Z",
    "bid": 4496.7,
    "ofrQty": 477,
    "bidQty": 477,
    "_id": "62613a15b7abb228586f44c1",
    "ofr": 4497.6
  },
  {
    "timestamp": "2022-04-21T11:03:48.960Z",
    "bid": 4496.7,
    "ofrQty": 477,
    "bidQty": 477,
    "_id": "62613a15b7abb228586f44c2",
    "ofr": 4497.6
  },
  {
    "timestamp": "2022-04-21T11:03:48.955Z",
    "bid": 4496.6,
    "ofrQty": 477,
    "bidQty": 477,
    "_id": "62613a15b7abb228586f44c3",
    "ofr": 4497.6
  },
  {
    "timestamp": "2022-04-21T11:03:48.964Z",
    "bid": 4496.7,
    "ofrQty": 477,
    "bidQty": 477,
    "_id": "62613a15b7abb228586f44c4",
    "ofr": 4497.7
  },
  {
    "timestamp": "2022-04-21T11:03:49.075Z",
    "bid": 4496.8,
    "ofrQty": 477,
    "bidQty": 477,
    "_id": "62613a15b7abb228586f44c5",
    "ofr": 4497.7
  },
  {
    "timestamp": "2022-04-21T11:03:49.076Z",
    "bid": 4496.8,
    "ofrQty": 477,
    "bidQty": 477,
    "_id": "62613a15b7abb228586f44c6",
    "ofr": 4497.8
  },
  {
    "timestamp": "2022-04-21T11:03:49.993Z",
    "bid": 4496.6,
    "ofrQty": 477,
    "bidQty": 477,
    "_id": "62613a16b7abb228586f44c7",
    "ofr": 4498.1
  },
  {
    "timestamp": "2022-04-21T11:03:50.010Z",
    "bid": 4496.8,
    "ofrQty": 477,
    "bidQty": 477,
    "_id": "62613a16b7abb228586f44c8",
    "ofr": 4497.8
  },
  {
    "timestamp": "2022-04-21T11:03:50.047Z",
    "bid": 4496.9,
    "ofrQty": 477,
    "bidQty": 477,
    "_id": "62613a16b7abb228586f44c9",
    "ofr": 4497.8
  },
  {
    "timestamp": "2022-04-21T11:03:50.266Z",
    "bid": 4496.8,
    "ofrQty": 477,
    "bidQty": 477,
    "_id": "62613a16b7abb228586f44ca",
    "ofr": 4497.8
  },
  {
    "timestamp": "2022-04-21T11:03:52.474Z",
    "bid": 4496.7,
    "ofrQty": 477,
    "bidQty": 477,
    "_id": "62613a18b7abb228586f44cb",
    "ofr": 4497.7
  },
  {
    "timestamp": "2022-04-21T11:03:56.683Z",
    "bid": 4496.8,
    "ofrQty": 477,
    "bidQty": 477,
    "_id": "62613a1cb7abb228586f44cc",
    "ofr": 4497.8
  },
  {
    "timestamp": "2022-04-21T11:03:58.314Z",
    "bid": 4496.7,
    "ofrQty": 477,
    "bidQty": 477,
    "_id": "62613a1eb7abb228586f44cd",
    "ofr": 4497.7
  },
  {
    "timestamp": "2022-04-21T11:04:00.212Z",
    "bid": 4496.8,
    "ofrQty": 477,
    "bidQty": 477,
    "_id": "62613a20b7abb228586f44ce",
    "ofr": 4497.7
  },
  {
    "timestamp": "2022-04-21T11:04:02.870Z",
    "bid": 4496.9,
    "ofrQty": 477,
    "bidQty": 477,
    "_id": "62613a22b7abb228586f44cf",
    "ofr": 4497.7
  },
  {
    "timestamp": "2022-04-21T11:04:02.872Z",
    "bid": 4496.9,
    "ofrQty": 477,
    "bidQty": 477,
    "_id": "62613a22b7abb228586f44d0",
    "ofr": 4497.8
  },
  {
    "timestamp": "2022-04-21T11:04:02.878Z",
    "bid": 4496.9,
    "ofrQty": 477,
    "bidQty": 477,
    "_id": "62613a22b7abb228586f44d1",
    "ofr": 4497.9
  },
  {
    "timestamp": "2022-04-21T11:04:04.062Z",
    "bid": 4496.9,
    "ofrQty": 477,
    "bidQty": 477,
    "_id": "62613a24b7abb228586f44d2",
    "ofr": 4497.8
  },
  {
    "timestamp": "2022-04-21T11:04:04.067Z",
    "bid": 4496.8,
    "ofrQty": 477,
    "bidQty": 477,
    "_id": "62613a24b7abb228586f44d3",
    "ofr": 4497.8
  },
  {
    "timestamp": "2022-04-21T11:04:07.413Z",
    "bid": 4496.6,
    "ofrQty": 477,
    "bidQty": 477,
    "_id": "62613a27b7abb228586f44d4",
    "ofr": 4498.1
  },
  {
    "timestamp": "2022-04-21T11:04:07.416Z",
    "bid": 4496.9,
    "ofrQty": 477,
    "bidQty": 477,
    "_id": "62613a27b7abb228586f44d5",
    "ofr": 4497.9
  },
  {
    "timestamp": "2022-04-21T11:04:07.419Z",
    "bid": 4497,
    "ofrQty": 477,
    "bidQty": 477,
    "_id": "62613a27b7abb228586f44d6",
    "ofr": 4497.9
  },
  {
    "timestamp": "2022-04-21T11:04:07.473Z",
    "bid": 4496.9,
    "ofrQty": 477,
    "bidQty": 477,
    "_id": "62613a27b7abb228586f44d7",
    "ofr": 4497.9
  },
  {
    "timestamp": "2022-04-21T11:04:07.491Z",
    "bid": 4497,
    "ofrQty": 477,
    "bidQty": 477,
    "_id": "62613a27b7abb228586f44d8",
    "ofr": 4498
  },
  {
    "timestamp": "2022-04-21T11:04:07.487Z",
    "bid": 4497,
    "ofrQty": 477,
    "bidQty": 477,
    "_id": "62613a27b7abb228586f44d9",
    "ofr": 4497.9
  },
  {
    "timestamp": "2022-04-21T11:04:07.517Z",
    "bid": 4496.8,
    "ofrQty": 477,
    "bidQty": 477,
    "_id": "62613a27b7abb228586f44da",
    "ofr": 4498.4
  },
  {
    "timestamp": "2022-04-21T11:04:07.531Z",
    "bid": 4496.8,
    "ofrQty": 477,
    "bidQty": 477,
    "_id": "62613a27b7abb228586f44db",
    "ofr": 4498.3
  },
  {
    "timestamp": "2022-04-21T11:04:08.197Z",
    "bid": 4497.2,
    "ofrQty": 477,
    "bidQty": 477,
    "_id": "62613a28b7abb228586f44dc",
    "ofr": 4498.2
  },
  {
    "timestamp": "2022-04-21T11:04:08.514Z",
    "bid": 4496.9,
    "ofrQty": 477,
    "bidQty": 477,
    "_id": "62613a28b7abb228586f44dd",
    "ofr": 4498.4
  },
  {
    "timestamp": "2022-04-21T11:04:09.088Z",
    "bid": 4497.1,
    "ofrQty": 477,
    "bidQty": 477,
    "_id": "62613a29b7abb228586f44de",
    "ofr": 4498.1
  },
  {
    "timestamp": "2022-04-21T11:04:10.750Z",
    "bid": 4497,
    "ofrQty": 477,
    "bidQty": 477,
    "_id": "62613a2ab7abb228586f44df",
    "ofr": 4498.1
  },
  {
    "timestamp": "2022-04-21T11:04:10.758Z",
    "bid": 4497,
    "ofrQty": 477,
    "bidQty": 477,
    "_id": "62613a2ab7abb228586f44e0",
    "ofr": 4498
  },
  {
    "timestamp": "2022-04-21T11:04:12.073Z",
    "bid": 4496.8,
    "ofrQty": 477,
    "bidQty": 477,
    "_id": "62613a2db7abb228586f44e1",
    "ofr": 4498.3
  },
  {
    "timestamp": "2022-04-21T11:04:12.328Z",
    "bid": 4497,
    "ofrQty": 477,
    "bidQty": 477,
    "_id": "62613a2db7abb228586f44e2",
    "ofr": 4498
  },
  {
    "timestamp": "2022-04-21T11:04:12.842Z",
    "bid": 4496.8,
    "ofrQty": 477,
    "bidQty": 477,
    "_id": "62613a2db7abb228586f44e3",
    "ofr": 4498.3
  },
  {
    "timestamp": "2022-04-21T11:04:13.372Z",
    "bid": 4497,
    "ofrQty": 477,
    "bidQty": 477,
    "_id": "62613a2eb7abb228586f44e4",
    "ofr": 4498
  },
  {
    "timestamp": "2022-04-21T11:04:14.527Z",
    "bid": 4497,
    "ofrQty": 477,
    "bidQty": 477,
    "_id": "62613a2eb7abb228586f44e5",
    "ofr": 4497.9
  },
  {
    "timestamp": "2022-04-21T11:04:14.530Z",
    "bid": 4496.9,
    "ofrQty": 477,
    "bidQty": 477,
    "_id": "62613a2eb7abb228586f44e6",
    "ofr": 4497.9
  },
  {
    "timestamp": "2022-04-21T11:04:15.987Z",
    "bid": 4496.6,
    "ofrQty": 477,
    "bidQty": 477,
    "_id": "62613a30b7abb228586f44e7",
    "ofr": 4498.1
  },
  {
    "timestamp": "2022-04-21T11:04:16.046Z",
    "bid": 4496.8,
    "ofrQty": 477,
    "bidQty": 477,
    "_id": "62613a30b7abb228586f44e8",
    "ofr": 4497.8
  },
  {
    "timestamp": "2022-04-21T11:04:16.145Z",
    "bid": 4496.8,
    "ofrQty": 477,
    "bidQty": 477,
    "_id": "62613a30b7abb228586f44e9",
    "ofr": 4497.7
  },
  {
    "timestamp": "2022-04-21T11:04:16.763Z",
    "bid": 4496.8,
    "ofrQty": 477,
    "bidQty": 477,
    "_id": "62613a30b7abb228586f44ea",
    "ofr": 4497.8
  },
  {
    "timestamp": "2022-04-21T11:04:17.692Z",
    "bid": 4496.9,
    "ofrQty": 477,
    "bidQty": 477,
    "_id": "62613a31b7abb228586f44eb",
    "ofr": 4497.9
  },
  {
    "timestamp": "2022-04-21T11:04:17.647Z",
    "bid": 4496.6,
    "ofrQty": 477,
    "bidQty": 477,
    "_id": "62613a31b7abb228586f44ec",
    "ofr": 4498.1
  },
  {
    "timestamp": "2022-04-21T11:04:19.038Z",
    "bid": 4496.9,
    "ofrQty": 477,
    "bidQty": 476.9,
    "_id": "62613a33b7abb228586f44ed",
    "ofr": 4497.9
  },
  {
    "timestamp": "2022-04-21T11:04:20.096Z",
    "bid": 4496.9,
    "ofrQty": 477,
    "bidQty": 477,
    "_id": "62613a34b7abb228586f44ee",
    "ofr": 4497.8
  },
  {
    "timestamp": "2022-04-21T11:04:20.101Z",
    "bid": 4496.8,
    "ofrQty": 477,
    "bidQty": 477,
    "_id": "62613a34b7abb228586f44ef",
    "ofr": 4497.8
  },
  {
    "timestamp": "2022-04-21T11:04:21.046Z",
    "bid": 4496.6,
    "ofrQty": 477,
    "bidQty": 477,
    "_id": "62613a35b7abb228586f44f0",
    "ofr": 4498.1
  },
  {
    "timestamp": "2022-04-21T11:04:21.097Z",
    "bid": 4496.9,
    "ofrQty": 477,
    "bidQty": 477,
    "_id": "62613a35b7abb228586f44f1",
    "ofr": 4497.9
  },
  {
    "timestamp": "2022-04-21T11:04:21.801Z",
    "bid": 4496.6,
    "ofrQty": 477,
    "bidQty": 477,
    "_id": "62613a35b7abb228586f44f2",
    "ofr": 4498.1
  },
  {
    "timestamp": "2022-04-21T11:04:22.955Z",
    "bid": 4496.9,
    "ofrQty": 477,
    "bidQty": 477,
    "_id": "62613a37b7abb228586f44f3",
    "ofr": 4497.9
  },
  {
    "timestamp": "2022-04-21T11:04:22.956Z",
    "bid": 4497,
    "ofrQty": 477,
    "bidQty": 477,
    "_id": "62613a37b7abb228586f44f4",
    "ofr": 4498
  },
  {
    "timestamp": "2022-04-21T11:04:22.957Z",
    "bid": 4497,
    "ofrQty": 477,
    "bidQty": 477,
    "_id": "62613a37b7abb228586f44f5",
    "ofr": 4498.1
  },
  {
    "timestamp": "2022-04-21T11:04:22.958Z",
    "bid": 4497.2,
    "ofrQty": 477,
    "bidQty": 477,
    "_id": "62613a37b7abb228586f44f6",
    "ofr": 4498.2
  },
  {
    "timestamp": "2022-04-21T11:04:22.968Z",
    "bid": 4497.2,
    "ofrQty": 477,
    "bidQty": 477,
    "_id": "62613a37b7abb228586f44f7",
    "ofr": 4498.1
  },
  {
    "timestamp": "2022-04-21T11:04:23.635Z",
    "bid": 4497.1,
    "ofrQty": 477,
    "bidQty": 477,
    "_id": "62613a37b7abb228586f44f8",
    "ofr": 4498.1
  },
  {
    "timestamp": "2022-04-21T11:04:23.637Z",
    "bid": 4497.2,
    "ofrQty": 477,
    "bidQty": 477,
    "_id": "62613a37b7abb228586f44f9",
    "ofr": 4498.1
  },
  {
    "timestamp": "2022-04-21T11:04:25.007Z",
    "bid": 4497.1,
    "ofrQty": 477,
    "bidQty": 477,
    "_id": "62613a39b7abb228586f44fa",
    "ofr": 4498
  },
  {
    "timestamp": "2022-04-21T11:04:25.007Z",
    "bid": 4497.1,
    "ofrQty": 477,
    "bidQty": 477,
    "_id": "62613a39b7abb228586f44fb",
    "ofr": 4497.9
  },
  {
    "timestamp": "2022-04-21T11:04:25.018Z",
    "bid": 4496.7,
    "ofrQty": 477,
    "bidQty": 477,
    "_id": "62613a39b7abb228586f44fc",
    "ofr": 4497.7
  },
  {
    "timestamp": "2022-04-21T11:04:25.008Z",
    "bid": 4497.1,
    "ofrQty": 477,
    "bidQty": 477,
    "_id": "62613a39b7abb228586f44fd",
    "ofr": 4498
  },
  {
    "timestamp": "2022-04-21T11:04:25.041Z",
    "bid": 4496.3,
    "ofrQty": 477,
    "bidQty": 477,
    "_id": "62613a39b7abb228586f44fe",
    "ofr": 4497.9
  },
  {
    "timestamp": "2022-04-21T11:04:25.112Z",
    "bid": 4496.4,
    "ofrQty": 477,
    "bidQty": 477,
    "_id": "62613a39b7abb228586f44ff",
    "ofr": 4497.9
  },
  {
    "timestamp": "2022-04-21T11:04:25.113Z",
    "bid": 4496.7,
    "ofrQty": 477,
    "bidQty": 477,
    "_id": "62613a39b7abb228586f4500",
    "ofr": 4497.7
  },
  {
    "timestamp": "2022-04-21T11:04:25.114Z",
    "bid": 4496.4,
    "ofrQty": 477,
    "bidQty": 477,
    "_id": "62613a39b7abb228586f4501",
    "ofr": 4497.9
  },
  {
    "timestamp": "2022-04-21T11:04:25.123Z",
    "bid": 4496.7,
    "ofrQty": 477,
    "bidQty": 477,
    "_id": "62613a39b7abb228586f4502",
    "ofr": 4497.7
  },
  {
    "timestamp": "2022-04-21T11:04:25.302Z",
    "bid": 4496.4,
    "ofrQty": 477,
    "bidQty": 477,
    "_id": "62613a39b7abb228586f4503",
    "ofr": 4497.9
  },
  {
    "timestamp": "2022-04-21T11:04:25.372Z",
    "bid": 4496.7,
    "ofrQty": 477,
    "bidQty": 477,
    "_id": "62613a39b7abb228586f4504",
    "ofr": 4497.7
  },
  {
    "timestamp": "2022-04-21T11:04:26.295Z",
    "bid": 4496.8,
    "ofrQty": 477,
    "bidQty": 477,
    "_id": "62613a3ab7abb228586f4505",
    "ofr": 4497.7
  },
  {
    "timestamp": "2022-04-21T11:04:26.296Z",
    "bid": 4496.7,
    "ofrQty": 477,
    "bidQty": 477,
    "_id": "62613a3ab7abb228586f4506",
    "ofr": 4497.7
  },
  {
    "timestamp": "2022-04-21T11:04:27.082Z",
    "bid": 4496.5,
    "ofrQty": 477,
    "bidQty": 477,
    "_id": "62613a3bb7abb228586f4507",
    "ofr": 4498
  },
  {
    "timestamp": "2022-04-21T11:04:28.643Z",
    "bid": 4496.8,
    "ofrQty": 477,
    "bidQty": 477,
    "_id": "62613a3cb7abb228586f4508",
    "ofr": 4497.8
  },
  {
    "timestamp": "2022-04-21T11:04:28.923Z",
    "bid": 4497,
    "ofrQty": 477,
    "bidQty": 477,
    "_id": "62613a3cb7abb228586f450a",
    "ofr": 4498
  },
  {
    "timestamp": "2022-04-21T11:04:28.922Z",
    "bid": 4496.9,
    "ofrQty": 477,
    "bidQty": 477,
    "_id": "62613a3cb7abb228586f4509",
    "ofr": 4497.8
  },
  {
    "timestamp": "2022-04-21T11:04:28.931Z",
    "bid": 4496.8,
    "ofrQty": 477,
    "bidQty": 477,
    "_id": "62613a3cb7abb228586f450c",
    "ofr": 4498.3
  },
  {
    "timestamp": "2022-04-21T11:04:28.929Z",
    "bid": 4496.8,
    "ofrQty": 477,
    "bidQty": 477,
    "_id": "62613a3cb7abb228586f450b",
    "ofr": 4498.4
  },
  {
    "timestamp": "2022-04-21T11:04:28.933Z",
    "bid": 4497,
    "ofrQty": 477,
    "bidQty": 477,
    "_id": "62613a3cb7abb228586f450d",
    "ofr": 4498
  },
  {
    "timestamp": "2022-04-21T11:04:29.320Z",
    "bid": 4496.8,
    "ofrQty": 477,
    "bidQty": 477,
    "_id": "62613a3db7abb228586f450e",
    "ofr": 4498.3
  },
  {
    "timestamp": "2022-04-21T11:04:29.375Z",
    "bid": 4497.1,
    "ofrQty": 477,
    "bidQty": 477,
    "_id": "62613a3db7abb228586f450f",
    "ofr": 4498.1
  },
  {
    "timestamp": "2022-04-21T11:04:30.387Z",
    "bid": 4496.8,
    "ofrQty": 477,
    "bidQty": 477,
    "_id": "62613a3eb7abb228586f4510",
    "ofr": 4498.3
  },
  {
    "timestamp": "2022-04-21T11:04:30.460Z",
    "bid": 4497,
    "ofrQty": 477,
    "bidQty": 477,
    "_id": "62613a3eb7abb228586f4511",
    "ofr": 4498
  },
  {
    "timestamp": "2022-04-21T11:04:31.507Z",
    "bid": 4497.1,
    "ofrQty": 477,
    "bidQty": 477,
    "_id": "62613a3fb7abb228586f4512",
    "ofr": 4498.1
  },
  {
    "timestamp": "2022-04-21T11:04:31.509Z",
    "bid": 4496.9,
    "ofrQty": 477,
    "bidQty": 477,
    "_id": "62613a3fb7abb228586f4513",
    "ofr": 4498.4
  },
  {
    "timestamp": "2022-04-21T11:04:31.511Z",
    "bid": 4497.2,
    "ofrQty": 477,
    "bidQty": 477,
    "_id": "62613a3fb7abb228586f4514",
    "ofr": 4498.2
  },
  {
    "timestamp": "2022-04-21T11:04:31.966Z",
    "bid": 4497.2,
    "ofrQty": 477,
    "bidQty": 477,
    "_id": "62613a40b7abb228586f4515",
    "ofr": 4498.1
  },
  {
    "timestamp": "2022-04-21T11:04:31.974Z",
    "bid": 4497.1,
    "ofrQty": 477,
    "bidQty": 477,
    "_id": "62613a40b7abb228586f4516",
    "ofr": 4498.1
  },
  {
    "timestamp": "2022-04-21T11:04:32.511Z",
    "bid": 4497,
    "ofrQty": 477,
    "bidQty": 477,
    "_id": "62613a40b7abb228586f4517",
    "ofr": 4498.1
  },
  {
    "timestamp": "2022-04-21T11:04:32.515Z",
    "bid": 4497,
    "ofrQty": 477,
    "bidQty": 477,
    "_id": "62613a40b7abb228586f4518",
    "ofr": 4498
  }
]
